README.md
setup.py
eml/__init__.py
eml/eml_2_1_1/__init__.py
eml/eml_2_2_0/__init__.py
eml/eml_2_2_0/eml.py
eml/gbif_1_1/__init__.py
python_eml.egg-info/PKG-INFO
python_eml.egg-info/SOURCES.txt
python_eml.egg-info/dependency_links.txt
python_eml.egg-info/not-zip-safe
python_eml.egg-info/top_level.txt