Metadata-Version: 2.1
Name: python-eml
Version: 0.0.2
Summary: Python package containing dataclasses for the Ecological Metadata Language (EML) standard
Home-page: https://github.com/pieterprovoost/python-eml
Author: Pieter Provoost
Author-email: pieterprovoost@gmail.com
License: MIT
